linux_do_mcp/__init__.py
linux_do_mcp/main.py
linux_do_mcp-0.1.4.dist-info/METADATA
linux_do_mcp-0.1.4.dist-info/WHEEL
linux_do_mcp-0.1.4.dist-info/entry_points.txt
linux_do_mcp-0.1.4.dist-info/RECORD
